stac_mcp/__init__.py
stac_mcp/__main__.py
stac_mcp/observability.py
stac_mcp/server.py
stac_mcp/prompts/__init__.py
stac_mcp/prompts/prompts.py
stac_mcp/tools/__init__.py
stac_mcp/tools/client.py
stac_mcp/tools/estimate_data_size.py
stac_mcp/tools/execution.py
stac_mcp/tools/get_aggregations.py
stac_mcp/tools/get_collection.py
stac_mcp/tools/get_conformance.py
stac_mcp/tools/get_item.py
stac_mcp/tools/get_queryables.py
stac_mcp/tools/get_root.py
stac_mcp/tools/params.py
stac_mcp/tools/search_collections.py
stac_mcp/tools/search_items.py
stac_mcp/tools/sensor_dtypes.py
stac_mcp/utils/__init__.py
stac_mcp/utils/tabular.py
stac_mcp/utils/today.py
stac_mcp-2.1.2.dist-info/METADATA
stac_mcp-2.1.2.dist-info/WHEEL
stac_mcp-2.1.2.dist-info/entry_points.txt
stac_mcp-2.1.2.dist-info/licenses/LICENSE
stac_mcp-2.1.2.dist-info/RECORD
