Metadata-Version: 2.4
Name: stac-mcp
Version: 2.1.2
Summary: An MCP Server for STAC requests
Author: BnJam
License: Apache-2.0
License-File: LICENSE
Classifier: Development Status :: 3 - Alpha
Classifier: Intended Audience :: Developers
Classifier: License :: OSI Approved :: Apache Software License
Classifier: Programming Language :: Python :: 3
Classifier: Programming Language :: Python :: 3.11
Classifier: Programming Language :: Python :: 3.12
Requires-Python: >=3.11
Requires-Dist: adlfs>=2025.8.0
Requires-Dist: anyio>=3.7.0
Requires-Dist: certifi>=2025.10.5
Requires-Dist: coverage>=7.10.7
Requires-Dist: fastapi>=0.119.0
Requires-Dist: fastmcp>=2.0.0
Requires-Dist: gcsfs>=2025.9.0
Requires-Dist: numpy>=2.3.3
Requires-Dist: odc-stac>=0.3.0
Requires-Dist: pyarrow>=21.0.0
Requires-Dist: pydantic>=2.11.0
Requires-Dist: pystac-client>=0.7.0
Requires-Dist: pystac>=1.8.0
Requires-Dist: pytest-asyncio>=1.2.0
Requires-Dist: pytest>=8.4.2
Requires-Dist: rasterio>=1.3.9
Requires-Dist: requests>=2.31.0
Requires-Dist: rioxarray>=0.19.0
Requires-Dist: s3fs>=2025.9.0
Requires-Dist: shapely>=2.0.0
Requires-Dist: viewtif>=0.2.4
Requires-Dist: xarray>=2023.1.0
Requires-Dist: zarr>=3.1.3
Provides-Extra: dev
Requires-Dist: fastapi; extra == 'dev'
Requires-Dist: httpx; extra == 'dev'
Requires-Dist: pytest-asyncio>=0.21.0; extra == 'dev'
Requires-Dist: pytest-cov; extra == 'dev'
Requires-Dist: pytest>=7.0.0; extra == 'dev'
Requires-Dist: requests; extra == 'dev'
Requires-Dist: respx; extra == 'dev'
Requires-Dist: ruff>=0.5.0; extra == 'dev'
